polibeepsync/__init__.py
polibeepsync/beep.pem
polibeepsync/cmdlineparser.py
polibeepsync/common.py
polibeepsync/custom_qt5_elements.py
polibeepsync/filesettings.py
polibeepsync/icone_rc.py
polibeepsync/new_gui.ui
polibeepsync/qtgui.py
polibeepsync/ui_resizable.py
polibeepsync/utils.py
poliBeePsync-0.7.2.dist-info/LICENSE
poliBeePsync-0.7.2.dist-info/LICENSE.old
poliBeePsync-0.7.2.dist-info/METADATA
poliBeePsync-0.7.2.dist-info/WHEEL
poliBeePsync-0.7.2.dist-info/entry_points.txt
poliBeePsync-0.7.2.dist-info/top_level.txt
poliBeePsync-0.7.2.dist-info/RECORD
