Metadata-Version: 2.1
Name: poliBeePsync
Version: 0.7.2
Summary: Sync files from https://beep.metid.polimi.it (for students of Politecnico di Milano)
Home-page: https://github.com/Jacotsu/polibeepsync
Author: Davide Olianas, Raffaele Di Campli
Author-email: ubuntupk@gmail.com, dcdrj.pub@gmail.com
License: GPLv3+
Platform: UNKNOWN
Classifier: Development Status :: 4 - Beta
Classifier: Environment :: X11 Applications :: Qt
Classifier: Intended Audience :: Education
Classifier: License :: OSI Approved :: GNU General Public License v3 or later (GPLv3+)
Classifier: Natural Language :: English
Classifier: Operating System :: OS Independent
Classifier: Programming Language :: Python :: 3.7
Requires-Python: >=3.7
Requires-Dist: appdirs
Requires-Dist: beautifulsoup4
Requires-Dist: keyring
Requires-Dist: lxml
Requires-Dist: pyparsing
Requires-Dist: PyQt5
Requires-Dist: PySide2
Requires-Dist: requests
Requires-Dist: signalslot
